streamlink/__init__.py
streamlink/_version.py
streamlink/api.py
streamlink/buffers.py
streamlink/cache.py
streamlink/compat.py
streamlink/exceptions.py
streamlink/logger.py
streamlink/options.py
streamlink/session.py
streamlink/packages/__init__.py
streamlink/packages/requests_file.py
streamlink/packages/flashmedia/__init__.py
streamlink/packages/flashmedia/amf.py
streamlink/packages/flashmedia/box.py
streamlink/packages/flashmedia/compat.py
streamlink/packages/flashmedia/error.py
streamlink/packages/flashmedia/f4v.py
streamlink/packages/flashmedia/flv.py
streamlink/packages/flashmedia/ordereddict.py
streamlink/packages/flashmedia/packet.py
streamlink/packages/flashmedia/tag.py
streamlink/packages/flashmedia/types.py
streamlink/packages/flashmedia/util.py
streamlink/plugin/__init__.py
streamlink/plugin/plugin.py
streamlink/plugin/api/__init__.py
streamlink/plugin/api/http_session.py
streamlink/plugin/api/mapper.py
streamlink/plugin/api/support_plugin.py
streamlink/plugin/api/useragents.py
streamlink/plugin/api/utils.py
streamlink/plugin/api/validate.py
streamlink/plugins/__init__.py
streamlink/plugins/abematv.py
streamlink/plugins/abweb.py
streamlink/plugins/adultswim.py
streamlink/plugins/afreeca.py
streamlink/plugins/akamaihd.py
streamlink/plugins/albavision.py
streamlink/plugins/aljazeeraen.py
streamlink/plugins/animelab.py
streamlink/plugins/app17.py
streamlink/plugins/ard_live.py
streamlink/plugins/ard_mediathek.py
streamlink/plugins/artetv.py
streamlink/plugins/atresplayer.py
streamlink/plugins/bbciplayer.py
streamlink/plugins/beattv.py
streamlink/plugins/bfmtv.py
streamlink/plugins/bigo.py
streamlink/plugins/bilibili.py
streamlink/plugins/bloomberg.py
streamlink/plugins/brightcove.py
streamlink/plugins/btsports.py
streamlink/plugins/btv.py
streamlink/plugins/canalplus.py
streamlink/plugins/cdnbg.py
streamlink/plugins/ceskatelevize.py
streamlink/plugins/cinergroup.py
streamlink/plugins/clubbingtv.py
streamlink/plugins/cnews.py
streamlink_lanroth-1.4.1.999.dist-info/LICENSE
streamlink_lanroth-1.4.1.999.dist-info/METADATA
streamlink_lanroth-1.4.1.999.dist-info/WHEEL
streamlink_lanroth-1.4.1.999.dist-info/entry_points.txt
streamlink_lanroth-1.4.1.999.dist-info/top_level.txt
streamlink_lanroth-1.4.1.999.dist-info/RECORD
