Metadata-Version: 2.1
Name: streamlink-lanroth
Version: 1.4.1.999
Summary: Streamlink is command-line utility that extracts streams from various services and pipes them into a video player of choice.
Home-page: https://github.com/streamlink/streamlink
Author: Streamlink
Author-email: charlie@charliedrage.com
License: Simplified BSD
Project-URL: Documentation, https://streamlink.github.io/
Project-URL: Tracker, https://github.com/streamlink/streamlink/issues
Project-URL: Source, https://github.com/streamlink/streamlink
Project-URL: Funding, https://opencollective.com/streamlink
Platform: UNKNOWN
Classifier: Development Status :: 5 - Production/Stable
Classifier: License :: OSI Approved :: BSD License
Classifier: Environment :: Console
Classifier: Intended Audience :: End Users/Desktop
Classifier: Operating System :: POSIX
Classifier: Operating System :: Microsoft :: Windows
Classifier: Operating System :: MacOS
Classifier: Programming Language :: Python :: 2.7
Classifier: Programming Language :: Python :: 3.5
Classifier: Programming Language :: Python :: 3.6
Classifier: Programming Language :: Python :: 3.7
Classifier: Programming Language :: Python :: 3.8
Classifier: Topic :: Internet :: WWW/HTTP
Classifier: Topic :: Multimedia :: Sound/Audio
Classifier: Topic :: Multimedia :: Video
Classifier: Topic :: Utilities
Requires-Python: >=2.7, !=3.0.*, !=3.1.*, !=3.2.*, !=3.3.*, !=3.4.*, <4
Requires-Dist: requests (<3.0,>=2.21.0)
Requires-Dist: isodate
Requires-Dist: websocket-client
Requires-Dist: PySocks (!=1.5.7,>=1.5.6)
Requires-Dist: pycryptodome (<4,>=3.4.3)
Requires-Dist: iso-639
Requires-Dist: iso3166
Requires-Dist: futures ; python_version < "3.0"
Requires-Dist: urllib3[secure] (>=1.23) ; python_version < "3.0"
Requires-Dist: win-inet-pton ; python_version < "3.0" and platform_system == "Windows"
Requires-Dist: backports.shutil-which ; python_version < "3.3"
Requires-Dist: backports.shutil-get-terminal-size ; python_version < "3.3"
Requires-Dist: singledispatch ; python_version < "3.4"
